adpred/ADpred.py
adpred/__init__.py
adpred/lib/__init__.py
adpred/lib/run-adpred.py
adpred/lib/utils.py
adpred/model/ADpred.h5
adpred/model/ADpred.json
adpred-1.3.2.data/scripts/run-adpred
adpred-1.3.2.dist-info/licenses/LICENSE
adpred-1.3.2.dist-info/METADATA
adpred-1.3.2.dist-info/WHEEL
adpred-1.3.2.dist-info/top_level.txt
adpred-1.3.2.dist-info/RECORD
