Metadata-Version: 2.4
Name: adpred
Version: 1.3.2
Summary: Prediction of Transcription Activation Domains from protein sequences
Home-page: https://github.com/FredHutch/adpred-pkg
Author: Ariel Erijman
Author-email: aerijman@fredhutch.org, aerijman@neb.com
Classifier: Programming Language :: Python :: 3
Classifier: License :: OSI Approved :: MIT License
Classifier: Operating System :: OS Independent
Requires-Python: >=3.9
License-File: LICENSE
Requires-Dist: keras==3.11.3
Requires-Dist: numpy==2.3.3
Requires-Dist: pandas==2.3.2
Requires-Dist: plotly==6.3.0
Requires-Dist: requests==2.32.5
Requires-Dist: requests-oauthlib==2.0.0
Requires-Dist: scikit-learn==1.7.2
Requires-Dist: tensorflow==2.20.0
Dynamic: author
Dynamic: author-email
Dynamic: classifier
Dynamic: description
Dynamic: description-content-type
Dynamic: home-page
Dynamic: license-file
Dynamic: requires-dist
Dynamic: requires-python
Dynamic: summary
